vcfpy2/__init__.py
vcfpy2/bgzf.py
vcfpy2/compat.py
vcfpy2/exceptions.py
vcfpy2/header.py
vcfpy2/parser.py
vcfpy2/reader.py
vcfpy2/record.py
vcfpy2/writer.py
vcfpy2-0.1.2.dist-info/AUTHORS.rst
vcfpy2-0.1.2.dist-info/LICENSE
vcfpy2-0.1.2.dist-info/METADATA
vcfpy2-0.1.2.dist-info/WHEEL
vcfpy2-0.1.2.dist-info/top_level.txt
vcfpy2-0.1.2.dist-info/RECORD
