Metadata-Version: 2.1
Name: vcfpy2
Version: 0.1.2
Summary: Python 3 VCF library, based on vcfpy.
Home-page: https://github.com/robertopreste/vcfpy2
Author: Roberto Preste
Author-email: robertopreste@gmail.com
License: MIT license
Keywords: vcfpy2
Platform: UNKNOWN
Classifier: Development Status :: 2 - Pre-Alpha
Classifier: Intended Audience :: Developers
Classifier: License :: OSI Approved :: MIT License
Classifier: Natural Language :: English
Classifier: Programming Language :: Python :: 3
Classifier: Programming Language :: Python :: 3.5
Classifier: Programming Language :: Python :: 3.6
Classifier: Programming Language :: Python :: 3.7
Requires-Dist: pysam (>=0.10.0)
